kwandl.py
kwandl-0.2.0.dist-info/LICENSE
kwandl-0.2.0.dist-info/METADATA
kwandl-0.2.0.dist-info/WHEEL
kwandl-0.2.0.dist-info/top_level.txt
kwandl-0.2.0.dist-info/RECORD
