Metadata-Version: 2.1
Name: kwandl
Version: 0.2.0
Summary: Keyword arguments handled
Home-page: https://github.com/egpbos/kwandl
Author: E. G. Patrick Bos
Author-email: p.bos@esciencecenter.nl
License: UNKNOWN
Project-URL: Bug Tracker, https://github.com/egpbos/kwandl/issues
Keywords: kwargs,python
Platform: UNKNOWN
Classifier: Development Status :: 2 - Pre-Alpha
Classifier: Intended Audience :: Developers
Classifier: License :: OSI Approved :: Apache Software License
Classifier: Natural Language :: English
Classifier: Programming Language :: Python :: 3
Classifier: Programming Language :: Python :: 3.7
Classifier: Programming Language :: Python :: 3.8
Classifier: Programming Language :: Python :: 3.9
Classifier: Programming Language :: Python :: 3.10
License-File: LICENSE
Requires-Dist: astunparse ; python_version < "3.9"
Provides-Extra: dev
Requires-Dist: bump2version ; extra == 'dev'
Requires-Dist: coverage[toml] ; extra == 'dev'
Requires-Dist: prospector[with_pyroma] ; extra == 'dev'
Requires-Dist: isort ; extra == 'dev'
Requires-Dist: pytest ; extra == 'dev'
Requires-Dist: pytest-cov ; extra == 'dev'
Requires-Dist: tox ; extra == 'dev'
Provides-Extra: docs
Requires-Dist: sphinx ; extra == 'docs'
Requires-Dist: sphinx-rtd-theme ; extra == 'docs'
Requires-Dist: sphinx-autoapi ; extra == 'docs'
Requires-Dist: myst-parser ; extra == 'docs'
Provides-Extra: publishing
Requires-Dist: build ; extra == 'publishing'
Requires-Dist: twine ; extra == 'publishing'
Requires-Dist: wheel ; extra == 'publishing'
